gis_mcp/__init__.py
gis_mcp/geopandas_functions.py
gis_mcp/main.py
gis_mcp/mcp.py
gis_mcp/pyproj_functions.py
gis_mcp/pysal_functions.py
gis_mcp/rasterio_functions.py
gis_mcp/save_tool.py
gis_mcp/shapely_functions.py
gis_mcp/data/__init__.py
gis_mcp/data/administrative_boundaries.py
gis_mcp/data/climate.py
gis_mcp/data/ecology.py
gis_mcp/data/land_cover.py
gis_mcp/data/movement.py
gis_mcp/data/satellite_imagery.py
gis_mcp/visualize/__init__.py
gis_mcp/visualize/map_tool.py
gis_mcp/visualize/web_map_tool.py
iflow_mcp_gis_mcp-0.9.1.dist-info/METADATA
iflow_mcp_gis_mcp-0.9.1.dist-info/WHEEL
iflow_mcp_gis_mcp-0.9.1.dist-info/entry_points.txt
iflow_mcp_gis_mcp-0.9.1.dist-info/licenses/LICENSE
iflow_mcp_gis_mcp-0.9.1.dist-info/RECORD
