Metadata-Version: 2.4
Name: iflow-mcp_gis-mcp
Version: 0.9.1
Summary: A Model Context Protocol (MCP) server implementation for GIS operations using GIS libraries
Author: Mahdi Nazari Ashani, Saba Kazemi, Shahab Esfandiar, Yasin Mohammadi, Homa Ganjali, GIS MCP Server Contributors
License: MIT License
License-File: LICENSE
Keywords: agentic AI,cdsapi,fiona,geopandas,geospatial,gis,llm,mcp,ogc,pygadm,pygbif,pyproj,pysal,rasterio,shapely
Classifier: Development Status :: 4 - Beta
Classifier: Intended Audience :: Developers
Classifier: License :: OSI Approved :: MIT License
Classifier: Programming Language :: Python :: 3
Classifier: Programming Language :: Python :: 3.10
Classifier: Programming Language :: Python :: 3.11
Requires-Python: >=3.10
Requires-Dist: esda>=2.7.0
Requires-Dist: fiona>=1.10.0
Requires-Dist: geopandas>=1.0.1
Requires-Dist: libpysal>=4.13.0
Requires-Dist: mcp==1.6.0
Requires-Dist: numpy<2.0,>=1.23
Requires-Dist: pandas>=2.0.0
Requires-Dist: pillow>=10.0.0
Requires-Dist: pyproj>=3.7.1
Requires-Dist: rasterio>=1.4.0
Requires-Dist: shapely>=2.1.0
Requires-Dist: spreg==1.8.3
Requires-Dist: tabulate>=0.9.0
Provides-Extra: administrative-boundaries
Requires-Dist: pygadm>=0.5.0; extra == 'administrative-boundaries'
Provides-Extra: all
Requires-Dist: cdsapi==0.7.6; extra == 'all'
Requires-Dist: folium>=0.15.0; extra == 'all'
Requires-Dist: osmnx>=2.0.0; extra == 'all'
Requires-Dist: planetary-computer>=1.0.0; extra == 'all'
Requires-Dist: pydeck>=0.9.0; extra == 'all'
Requires-Dist: pygadm>=0.5.0; extra == 'all'
Requires-Dist: pygbif>=0.6.4; extra == 'all'
Requires-Dist: pystac-client>=0.7.6; extra == 'all'
Requires-Dist: requests>=2.31; extra == 'all'
Requires-Dist: stackstac>=0.5.0; extra == 'all'
Requires-Dist: xarray>=2023.1.0; extra == 'all'
Provides-Extra: climate
Requires-Dist: cdsapi>=0.6.1; extra == 'climate'
Provides-Extra: ecology
Requires-Dist: pygbif>=0.6.4; extra == 'ecology'
Provides-Extra: land-cover
Requires-Dist: planetary-computer>=1.0.0; extra == 'land-cover'
Requires-Dist: pystac-client>=0.7.6; extra == 'land-cover'
Requires-Dist: requests>=2.31; extra == 'land-cover'
Requires-Dist: stackstac>=0.5.0; extra == 'land-cover'
Requires-Dist: xarray>=2023.1.0; extra == 'land-cover'
Provides-Extra: movement
Requires-Dist: osmnx>=2.0.0; extra == 'movement'
Provides-Extra: satellite-imagery
Requires-Dist: planetary-computer>=1.0.0; extra == 'satellite-imagery'
Requires-Dist: pystac-client>=0.7.6; extra == 'satellite-imagery'
Requires-Dist: requests>=2.31; extra == 'satellite-imagery'
Requires-Dist: stackstac>=0.5.0; extra == 'satellite-imagery'
Requires-Dist: xarray>=2023.1.0; extra == 'satellite-imagery'
Provides-Extra: visualize
Requires-Dist: folium>=0.15.0; extra == 'visualize'
Requires-Dist: pydeck>=0.9.0; extra == 'visualize'
